Metadata-Version: 2.1
Name: elementapi
Version: 0.4
Summary: element-iot api client lib
Home-page: https://github.com/ZennerIoT/python-elementapi
Download-URL: https://github.com/ZennerIoT/python-elementapi/archive/master.zip
Author: Stefan Reiser
Author-email: sr@zenner-iot.com
Keywords: client,rest,element-iot
Classifier: Development Status :: 3 - Alpha
Classifier: Intended Audience :: Developers
Classifier: License :: OSI Approved :: MIT License
Classifier: Programming Language :: Python :: 2.7
Classifier: Programming Language :: Python :: 3
